.gitignore
setup.py
docs/Makefile
docs/conf.py
docs/index.rst
docs/make.bat
docs/_themes/LICENSE
docs/_themes/README.rst
docs/_themes/flask_theme_support.py
docs/_themes/kr/layout.html
docs/_themes/kr/relations.html
docs/_themes/kr/theme.conf
docs/_themes/kr_small/layout.html
docs/_themes/kr_small/theme.conf
shingling/__init__.py
shingling/core.py
shingling.egg-info/PKG-INFO
shingling.egg-info/SOURCES.txt
shingling.egg-info/dependency_links.txt
shingling.egg-info/not-zip-safe
shingling.egg-info/requires.txt
shingling.egg-info/top_level.txt
shingling/templates/shingling.html