Metadata-Version: 1.0
Name: shingling
Version: 0.1
Summary: A library for making w shingles
Home-page: UNKNOWN
Author: Santhosh Thottingal
Author-email: santhosh.thottingal@gmail.com
License: LGPL-3.0
Platform: UNKNOWN
